Html_Flask_Install-0.1.3.data/data/src/app.py/app.py
Html_Flask_Install-0.1.3.data/scripts/run.sh
Html_Flask_Install-0.1.3.data/scripts/setup.sh
src/__init__.py
src/app.py
src/writefile_html.py
Html_Flask_Install-0.1.3.dist-info/LICENCE
Html_Flask_Install-0.1.3.dist-info/METADATA
Html_Flask_Install-0.1.3.dist-info/WHEEL
Html_Flask_Install-0.1.3.dist-info/top_level.txt
Html_Flask_Install-0.1.3.dist-info/RECORD
